LICENSE
MANIFEST.in
README.md
setup.py
iterstuff/__init__.py
iterstuff/lookahead.py
iterstuff/recipes.py
iterstuff/tests.py
iterstuff.egg-info/PKG-INFO
iterstuff.egg-info/SOURCES.txt
iterstuff.egg-info/dependency_links.txt
iterstuff.egg-info/top_level.txt
iterstuff.egg-info/zip-safe