Metadata-Version: 1.1
Name: iterstuff
Version: 1.0.2
Summary: Useful tools for working with iterators
Home-page: https://github.com/mobify/iterstuff
Author: Mobify
Author-email: product@mobify.com
License: MIT
Keywords: iterator generator development
Platform: UNKNOWN
Classifier: Development Status :: 5 - Production/Stable
Classifier: Intended Audience :: Developers
Classifier: Topic :: Software Development :: Libraries
Classifier: Topic :: Software Development :: Libraries :: Python Modules
Classifier: License :: OSI Approved :: MIT License
Classifier: Programming Language :: Python :: 2
Classifier: Programming Language :: Python :: 2.6
Classifier: Programming Language :: Python :: 2.7
